moesifasgi/__init__.py
moesifasgi/app_config.py
moesifasgi/async_iterator_wrapper.py
moesifasgi/backup.py
moesifasgi/client_ip.py
moesifasgi/event_logger.py
moesifasgi/event_mapper.py
moesifasgi/logger_helper.py
moesifasgi/middleware.py
moesifasgi/middleware_copy.py
moesifasgi/middleware_without_gr.py
moesifasgi/parse_body.py
moesifasgi/send_batch_events.py
moesifasgi/update_companies.py
moesifasgi/update_users.py
moesifasgi/version.py
moesifasgi-1.1.8.dist-info/licenses/LICENSE
moesifasgi-1.1.8.dist-info/METADATA
moesifasgi-1.1.8.dist-info/WHEEL
moesifasgi-1.1.8.dist-info/top_level.txt
moesifasgi-1.1.8.dist-info/RECORD
