Metadata-Version: 2.4
Name: moesifasgi
Version: 1.1.8
Summary: Moesif Middleware for Python ASGI based platforms (FastAPI & Others)
Home-page: https://www.moesif.com/docs/server-integration/python-asgi/
Author: Moesif, Inc
Author-email: keyur@moesif.com
License: Apache Software License
Keywords: log analysis restful api development debug asgi fastapi http middleware
Classifier: Development Status :: 5 - Production/Stable
Classifier: Intended Audience :: Developers
Classifier: Topic :: Internet :: Log Analysis
Classifier: Topic :: Software Development :: Debuggers
Classifier: Topic :: Software Development :: Libraries
Classifier: Topic :: Internet :: WWW/HTTP
Classifier: License :: OSI Approved :: Apache Software License
Classifier: Programming Language :: Python :: 3.6
Classifier: Programming Language :: Python :: 3.7
Classifier: Programming Language :: Python :: 3.8
Classifier: Programming Language :: Python :: 3.9
Classifier: Programming Language :: Python :: 3.10
Classifier: Programming Language :: Python :: 3.11
Classifier: Programming Language :: Python :: 3.12
Classifier: Programming Language :: Python :: 3.13
License-File: LICENSE
Requires-Dist: starlette>=0.16.0
Requires-Dist: moesifapi>=1.5.5
Requires-Dist: moesifpythonrequest>=0.3.4
Requires-Dist: packaging
Provides-Extra: dev
Provides-Extra: test
Requires-Dist: nose; extra == "test"
Dynamic: author
Dynamic: author-email
Dynamic: classifier
Dynamic: description
Dynamic: description-content-type
Dynamic: home-page
Dynamic: keywords
Dynamic: license
Dynamic: license-file
Dynamic: provides-extra
Dynamic: requires-dist
Dynamic: summary
